odoo/addons/ssi_transaction_terminate_mixin/README.rst
odoo/addons/ssi_transaction_terminate_mixin/__init__.py
odoo/addons/ssi_transaction_terminate_mixin/__manifest__.py
odoo/addons/ssi_transaction_terminate_mixin/demo/base_terminate_reason_demo.xml
odoo/addons/ssi_transaction_terminate_mixin/models/__init__.py
odoo/addons/ssi_transaction_terminate_mixin/models/base_terminate_reason.py
odoo/addons/ssi_transaction_terminate_mixin/models/ir_model.py
odoo/addons/ssi_transaction_terminate_mixin/models/mixin_transaction_terminate.py
odoo/addons/ssi_transaction_terminate_mixin/security/ir.model.access.csv
odoo/addons/ssi_transaction_terminate_mixin/static/description/icon.png
odoo/addons/ssi_transaction_terminate_mixin/templates/mixin_transaction_terminate_templates.xml
odoo/addons/ssi_transaction_terminate_mixin/views/base_terminate_reason_views.xml
odoo/addons/ssi_transaction_terminate_mixin/views/ir_model_views.xml
odoo/addons/ssi_transaction_terminate_mixin/wizards/__init__.py
odoo/addons/ssi_transaction_terminate_mixin/wizards/base_select_terminate_reason.py
odoo/addons/ssi_transaction_terminate_mixin/wizards/base_select_terminate_reason_views.xml
odoo14_addon_ssi_transaction_terminate_mixin-14.0.1.12.0.dist-info/METADATA
odoo14_addon_ssi_transaction_terminate_mixin-14.0.1.12.0.dist-info/WHEEL
odoo14_addon_ssi_transaction_terminate_mixin-14.0.1.12.0.dist-info/top_level.txt
odoo14_addon_ssi_transaction_terminate_mixin-14.0.1.12.0.dist-info/RECORD
